quqfin/__init__.py
quqfin/core/options.py
quqfin/core/algo_trading/strategies.py
quqfin/core/fixed_income/bonds.py
quqfin/core/market_making/orderbook.py
quqfin/core/options/black_scholes.py
quqfin/core/options/monte_carlo.py
quqfin/core/portfolio/optimization.py
quqfin/core/risk/var.py
quqfin/core/timeseries/models.py
quqfin-0.1.0.dist-info/METADATA
quqfin-0.1.0.dist-info/WHEEL
quqfin-0.1.0.dist-info/top_level.txt
quqfin-0.1.0.dist-info/RECORD
