Metadata-Version: 2.4
Name: quqfin
Version: 0.1.0
Summary: A quantum-accelerated quantitative finance library
Author-email: Shiwen An <sweynan@icloud.com>
Project-URL: Homepage, https://github.com/yourusername/quqfin
Project-URL: Documentation, https://quqfin.readthedocs.io
Requires-Python: >=3.8
Requires-Dist: numpy>=1.21.0
Requires-Dist: scipy>=1.7.0
Requires-Dist: pandas>=1.3.0
Requires-Dist: cupy>=11.0.0
Requires-Dist: cuquantum-python>=22.11.0
